{
  "symbols": {
    "SPY": {
      "label": "S&P 500",
      "upVolume": 4341820,
      "downVolume": 3801790,
      "flatVolume": 0,
      "barsUsed": 84,
      "lastBarTimestamp": 1784213640
    },
    "QQQ": {
      "label": "NASDAQ 100",
      "upVolume": 3785047,
      "downVolume": 3862547,
      "flatVolume": 0,
      "barsUsed": 84,
      "lastBarTimestamp": 1784213640
    },
    "DIA": {
      "label": "Dow 30",
      "upVolume": 576027,
      "downVolume": 425358,
      "flatVolume": 53374,
      "barsUsed": 82,
      "lastBarTimestamp": 1784213640
    },
    "IWM": {
      "label": "Russell 2000",
      "upVolume": 2701212,
      "downVolume": 2352763,
      "flatVolume": 0,
      "barsUsed": 84,
      "lastBarTimestamp": 1784213640
    }
  },
  "totalUpVolume": 11404106,
  "totalDownVolume": 10442458,
  "upDownRatio": 1.092,
  "_lastUpdated": "2026-07-16T14:55:30Z",
  "_failedSymbols": [],
  "_methodology": "Bar-direction proxy (1-min bar volume classified by close vs prior close), NOT tick-level aggressor-side (Lee-Ready) volume - that requires paid NBBO quote data."
}