{
  "symbols": {
    "SPY": {
      "label": "S&P 500",
      "upVolume": 469258,
      "downVolume": 618436,
      "flatVolume": 179301,
      "barsUsed": 14,
      "lastBarTimestamp": 1784900640
    },
    "QQQ": {
      "label": "NASDAQ 100",
      "upVolume": 1013372,
      "downVolume": 1329652,
      "flatVolume": 0,
      "barsUsed": 14,
      "lastBarTimestamp": 1784900640
    },
    "DIA": {
      "label": "Dow 30",
      "upVolume": 153736,
      "downVolume": 221695,
      "flatVolume": 0,
      "barsUsed": 14,
      "lastBarTimestamp": 1784900640
    },
    "IWM": {
      "label": "Russell 2000",
      "upVolume": 251218,
      "downVolume": 567079,
      "flatVolume": 0,
      "barsUsed": 14,
      "lastBarTimestamp": 1784900640
    }
  },
  "totalUpVolume": 1887584,
  "totalDownVolume": 2736862,
  "upDownRatio": 0.69,
  "_lastUpdated": "2026-07-24T13:45:21Z",
  "_failedSymbols": [],
  "_methodology": "Bar-direction proxy (1-min bar volume classified by close vs prior close), NOT tick-level aggressor-side (Lee-Ready) volume - that requires paid NBBO quote data."
}