{
  "es": {
    "ticker": "ES=F",
    "current": 7484.25,
    "previous": 7484.25
  },
  "nq": {
    "ticker": "NQ=F",
    "current": 28512.75,
    "previous": 28778.75
  },
  "ym": {
    "ticker": "YM=F",
    "current": 52257.0,
    "previous": 52073.0
  },
  "rty": {
    "ticker": "RTY=F",
    "current": 2965.9,
    "previous": 2955.2
  },
  "vix_spot": {
    "ticker": "^VIX",
    "current": 17.59,
    "previous": 18.65
  },
  "tnx": {
    "ticker": "^TNX",
    "current": 4.657,
    "previous": 4.598
  },
  "dxy_spot": {
    "ticker": "DX-Y.NYB",
    "current": 101.336,
    "previous": 100.99
  },
  "cl": {
    "ticker": "CL=F",
    "current": 87.95,
    "previous": 83.23
  },
  "_lastUpdated": "2026-07-24T15:42:26Z",
  "_failedSymbols": []
}